[
  {
    "year": 2023,
    "months": [
      {
        "month": {
          "number": 8,
          "name": "august"
        },
        "weeks": [
          {
            "week": 1,
            "learning": [
              {
                "image": {
                  "source": "html5.jpg",
                  "name": "HTML 5 logo"
                },
                "title": "HTML 5",
                "tasks": [
                  {
                    "name": "Tutorial W3Schools",
                    "status": "completed"
                  },
                  {
                    "name": "Exercises W3Schools",
                    "status": "completed"
                  },
                  {
                    "name": "Quiz W3Schools",
                    "status": "completed"
                  },
                  {
                    "name": "Tutorial CodeAcademy",
                    "status": "completed"
                  }
                ]
              }
            ],
            "projects": [
              {
                "image_source": "bridge.jpg",
                "image_name": "Bridge",
                "title": "My 27 Biography",
                "status": "completed",
                "tasks": []
              }
            ],
            "concepts": [
              {
                "name": "Flexbox",
                "technology": "MDB 5"
              },
              {
                "name": "Grid system",
                "technology": "MDB 5"
              },
              {
                "name": "Position",
                "technology": "MDB 5"
              },
              {
                "name": "Cards",
                "technology": "MDB 5"
              },
              {
                "name": "Icons",
                "technology": "MDB 5"
              }
            ],
            "working time": {
              "days": 5,
              "hours": 30,
              "notice": {}
            },
            "technologies": [
              {
                "image": "html-icon.png",
                "name": "HTML 5 logo"
              },
              {
                "image": "css-icon.png",
                "name": "CSS 3 logo"
              },
              {
                "image": "javascript-icon.png",
                "name": "Javascript logo"
              },
              {
                "image": "css-icon.png",
                "name": "CSS 3 logo"
              },
              {
                "image": "mdb5.png",
                "name": "MDBootstrap 5"
              }
            ]
          }
        ]
      },
      {
        "month": {
          "number": 9,
          "name": "september"
        },
        "weeks": [
          {
            "week": 2,
            "learning": [
              {
                "image": {
                  "source": "css3.jpg",
                  "name": "CSS 3 logo"
                },
                "title": "CSS 3",
                "tasks": [
                  {
                    "name": "Tutorial W3Schools",
                    "status": "completed"
                  },
                  {
                    "name": "Exercises W3Schools",
                    "status": "completed"
                  },
                  {
                    "name": "Quiz W3Schools",
                    "status": "completed"
                  },
                  {
                    "name": "Tutorial CodeAcademy",
                    "status": "completed"
                  }
                ]
              }
            ],
            "projects": [
              {
                "image_source": "bridge.jpg",
                "image_name": "Bridge",
                "title": "My 27 Biography",
                "status": "completed",
                "tasks": []
              }
            ],
            "concepts": [
              {
                "name": "Flexbox",
                "technology": "MDB 5"
              },
              {
                "name": "Grid system",
                "technology": "MDB 5"
              },
              {
                "name": "Position",
                "technology": "MDB 5"
              },
              {
                "name": "Group list",
                "technology": "MDB 5"
              },
              {
                "name": "Badge",
                "technology": "MDB 5"
              }
            ],
            "working time": {
              "days": 5,
              "hours": 30,
              "notice": {}
            },
            "technologies": [
              {
                "image": "html-icon.png",
                "name": "HTML 5 logo"
              },
              {
                "image": "css-icon.png",
                "name": "CSS 3 logo"
              },
              {
                "image": "javascript-icon.png",
                "name": "Javascript logo"
              },
              {
                "image": "css-icon.png",
                "name": "CSS 3 logo"
              },
              {
                "image": "mdb5.png",
                "name": "MDBootstrap 5"
              }
            ]
          }
        ]
      }
    ]
  },
  {
    "year": 2024,
    "months": []
  }
]
